{
  "streams": [
    {
      "title": "My Stream",
      "description": "Best stream ever!",
      "id": 1
    },
    {
      "title": "My Stream",
      "description": "Best stream ever!",
      "id": 2
    },
    {
      "title": "My Stream",
      "description": "Best stream ever!",
      "id": 3
    },
    {
      "title": "Programmatic routing",
      "description": "testing testing",
      "userId": "103433150577345909080",
      "id": 4
    },
    {
      "title": "ghfhg",
      "description": "ehrh",
      "userId": "103433150577345909080",
      "id": 5
    },
    {
      "title": "ffgw",
      "description": "2rwrw",
      "userId": "103433150577345909080",
      "id": 6
    },
    {
      "title": "jnjvkh",
      "description": "nknjvkj",
      "userId": "103433150577345909080",
      "id": 7
    },
    {
      "title": "vgeg",
      "description": "b",
      "userId": "103433150577345909080",
      "id": 8
    }
  ]
}